skyrl_tx-0.2.0.dist-info/licenses/LICENSE
tx/__init__.py
tx/layers/lora.py
tx/layers/util.py
tx/loaders/__init__.py
tx/loaders/chat.py
tx/loaders/common.py
tx/loaders/text.py
tx/models/__init__.py
tx/models/configs.py
tx/models/mnist.py
tx/models/qwen3.py
tx/models/types.py
tx/run/main.py
tx/run/train.py
tx/tinker/api.py
tx/tinker/config.py
tx/tinker/db_models.py
tx/tinker/engine.py
tx/tinker/loss_fns.py
tx/tinker/types.py
tx/tinker/extra/__init__.py
tx/tinker/extra/external_inference.py
tx/utils/generator.py
tx/utils/log.py
tx/utils/models.py
tx/utils/storage.py
skyrl_tx-0.2.0.dist-info/METADATA
skyrl_tx-0.2.0.dist-info/WHEEL
skyrl_tx-0.2.0.dist-info/entry_points.txt
skyrl_tx-0.2.0.dist-info/top_level.txt
skyrl_tx-0.2.0.dist-info/RECORD
