Metadata-Version: 2.4
Name: skyrl-tx
Version: 0.2.0
Summary: Unified API for training and inference
Requires-Python: >=3.11
License-File: LICENSE
Requires-Dist: datasets>=4.0.0
Requires-Dist: flax>=0.12.0
Requires-Dist: optax>=0.2.5
Requires-Dist: pillow>=11.3.0
Requires-Dist: rich>=14.1.0
Requires-Dist: safetensors>=0.6.2
Requires-Dist: transformers>=4.56.1
Requires-Dist: typer>=0.17.4
Requires-Dist: peft
Requires-Dist: hf_transfer
Requires-Dist: cloudpathlib>=0.23.0
Requires-Dist: jax>=0.8
Provides-Extra: gpu
Requires-Dist: jax[cuda12]>=0.7.2; extra == "gpu"
Provides-Extra: tpu
Requires-Dist: jax[tpu]>=0.7.2; extra == "tpu"
Provides-Extra: tinker
Requires-Dist: tinker>=0.2.1; extra == "tinker"
Requires-Dist: fastapi[standard]; extra == "tinker"
Requires-Dist: sqlmodel; extra == "tinker"
Requires-Dist: sqlalchemy[asyncio]; extra == "tinker"
Requires-Dist: aiosqlite; extra == "tinker"
Requires-Dist: asyncpg; extra == "tinker"
Requires-Dist: psycopg2-binary; extra == "tinker"
Provides-Extra: aws
Requires-Dist: cloudpathlib[s3]; extra == "aws"
Provides-Extra: gcp
Requires-Dist: cloudpathlib[gs]; extra == "gcp"
Provides-Extra: azure
Requires-Dist: cloudpathlib[azure]; extra == "azure"
Provides-Extra: dev
Requires-Dist: mkdocs; extra == "dev"
Requires-Dist: mkdocs-material; extra == "dev"
Requires-Dist: pytest; extra == "dev"
Requires-Dist: pytest-forked; extra == "dev"
Requires-Dist: torch; extra == "dev"
Requires-Dist: ty; extra == "dev"
Requires-Dist: cloudpathlib[s3]; extra == "dev"
Dynamic: license-file
